Metadata-Version: 1.1
Name: pyshark-legacy
Version: 0.3.8
Summary: Python wrapper for tshark, allowing python packet parsing using wireshark dissectors
Home-page: https://github.com/KimiNewt/pyshark
Author: KimiNewt
Author-email: UNKNOWN
License: UNKNOWN
Keywords: wireshark capture packets parsing packet
Platform: UNKNOWN
Classifier: License :: OSI Approved :: MIT License
Classifier: Programming Language :: Python :: 2
Classifier: Programming Language :: Python :: 3
